asyncalchemy/__init__.py
asyncalchemy/global_executor.py
asyncalchemy/session_committer.py
asyncalchemy/utils.py
asyncalchemy-1.1.4.dist-info/LICENSE
asyncalchemy-1.1.4.dist-info/WHEEL
asyncalchemy-1.1.4.dist-info/METADATA
asyncalchemy-1.1.4.dist-info/RECORD
