Metadata-Version: 2.1
Name: asyncalchemy
Version: 1.1.4
Summary: A thin async wrapper for SQLAlchemy sessions.
Home-page: https://github.com/claroty/AsyncAlchemy
License: Apache-2.0
Author: Claroty Open Source
Author-email: opensource@claroty.com
Requires-Python: >=3.6,<4.0
Classifier: License :: OSI Approved :: Apache Software License
Classifier: Programming Language :: Python :: 3
Classifier: Programming Language :: Python :: 3.6
Classifier: Programming Language :: Python :: 3.7
Classifier: Programming Language :: Python :: 3.8
Classifier: Programming Language :: Python :: 3.9
Requires-Dist: sqlalchemy (>=1.2.0,<1.4.0)
Project-URL: Documentation, https://github.com/claroty/AsyncAlchemy
